azul_voos/__init__.py
azul_voos/azul.py
azul_voos/dates.py
azul_voos/html_scraper.py
azul_voos/util.py
azul_voos-0.1.5.dist-info/METADATA
azul_voos-0.1.5.dist-info/WHEEL
azul_voos-0.1.5.dist-info/licenses/LICENSE
azul_voos-0.1.5.dist-info/licenses/LICENSE.chromedriver
azul_voos-0.1.5.dist-info/RECORD
