Metadata-Version: 2.1
Name: azul_voos
Version: 0.1.5
Summary: Scraping de dados de voo da empresa Azul utilizando selenium
Project-URL: Homepage, https://github.com/ricardostange/azul-voos
Project-URL: Bug Tracker, https://github.com/ricardostange/azul-voos/issues
Author-email: ricks <ricstange@gmail.com>
License-File: LICENSE
License-File: LICENSE.chromedriver
Classifier: License :: OSI Approved :: MIT License
Classifier: Operating System :: OS Independent
Classifier: Programming Language :: Python :: 3
Requires-Python: >=3.7
